{
  "season_type": "preseason",
  "week": 10,
  "year": 2025,
  "total_games": 14,
  "generated_date": "2025-08-24T00:33:53.270842",
  "games": [
    {
      "url": "https://www.espn.com/nfl/game/_/gameId/401772944",
      "game_id": "401772944",
      "date": "2025-11-07T01:15Z",
      "week": 10,
      "season_type": 2,
      "away_team": "LV",
      "home_team": "DEN",
      "matchup": "LV @ DEN"
    },
    {
      "url": "https://www.espn.com/nfl/game/_/gameId/401772636",
      "game_id": "401772636",
      "date": "2025-11-09T14:30Z",
      "week": 10,
      "season_type": 2,
      "away_team": "ATL",
      "home_team": "IND",
      "matchup": "ATL @ IND"
    },
    {
      "url": "https://www.espn.com/nfl/game/_/gameId/401772875",
      "game_id": "401772875",
      "date": "2025-11-09T18:00Z",
      "week": 10,
      "season_type": 2,
      "away_team": "NYG",
      "home_team": "CHI",
      "matchup": "NYG @ CHI"
    },
    {
      "url": "https://www.espn.com/nfl/game/_/gameId/401772771",
      "game_id": "401772771",
      "date": "2025-11-09T18:00Z",
      "week": 10,
      "season_type": 2,
      "away_team": "BUF",
      "home_team": "MIA",
      "matchup": "BUF @ MIA"
    },
    {
      "url": "https://www.espn.com/nfl/game/_/gameId/401772876",
      "game_id": "401772876",
      "date": "2025-11-09T18:00Z",
      "week": 10,
      "season_type": 2,
      "away_team": "BAL",
      "home_team": "MIN",
      "matchup": "BAL @ MIN"
    },
    {
      "url": "https://www.espn.com/nfl/game/_/gameId/401772769",
      "game_id": "401772769",
      "date": "2025-11-09T18:00Z",
      "week": 10,
      "season_type": 2,
      "away_team": "CLE",
      "home_team": "NYJ",
      "matchup": "CLE @ NYJ"
    },
    {
      "url": "https://www.espn.com/nfl/game/_/gameId/401772772",
      "game_id": "401772772",
      "date": "2025-11-09T18:00Z",
      "week": 10,
      "season_type": 2,
      "away_team": "NE",
      "home_team": "TB",
      "matchup": "NE @ TB"
    },
    {
      "url": "https://www.espn.com/nfl/game/_/gameId/401772877",
      "game_id": "401772877",
      "date": "2025-11-09T18:00Z",
      "week": 10,
      "season_type": 2,
      "away_team": "NO",
      "home_team": "CAR",
      "matchup": "NO @ CAR"
    },
    {
      "url": "https://www.espn.com/nfl/game/_/gameId/401772770",
      "game_id": "401772770",
      "date": "2025-11-09T18:00Z",
      "week": 10,
      "season_type": 2,
      "away_team": "JAX",
      "home_team": "HOU",
      "matchup": "JAX @ HOU"
    },
    {
      "url": "https://www.espn.com/nfl/game/_/gameId/401772773",
      "game_id": "401772773",
      "date": "2025-11-09T21:05Z",
      "week": 10,
      "season_type": 2,
      "away_team": "ARI",
      "home_team": "SEA",
      "matchup": "ARI @ SEA"
    },
    {
      "url": "https://www.espn.com/nfl/game/_/gameId/401772879",
      "game_id": "401772879",
      "date": "2025-11-09T21:25Z",
      "week": 10,
      "season_type": 2,
      "away_team": "LAR",
      "home_team": "SF",
      "matchup": "LAR @ SF"
    },
    {
      "url": "https://www.espn.com/nfl/game/_/gameId/401772878",
      "game_id": "401772878",
      "date": "2025-11-09T21:25Z",
      "week": 10,
      "season_type": 2,
      "away_team": "DET",
      "home_team": "WSH",
      "matchup": "DET @ WSH"
    },
    {
      "url": "https://www.espn.com/nfl/game/_/gameId/401772927",
      "game_id": "401772927",
      "date": "2025-11-10T01:20Z",
      "week": 10,
      "season_type": 2,
      "away_team": "PIT",
      "home_team": "LAC",
      "matchup": "PIT @ LAC"
    },
    {
      "url": "https://www.espn.com/nfl/game/_/gameId/401772630",
      "game_id": "401772630",
      "date": "2025-11-11T01:15Z",
      "week": 10,
      "season_type": 2,
      "away_team": "PHI",
      "home_team": "GB",
      "matchup": "PHI @ GB"
    }
  ]
}